__init__.py
artfetch/ArtFetch.py
artfetch/__init__.py
artfetch/config_default.yaml
artfetch/configuration.py
artfetch/view.py
artfetch/sources/__init__.py
artfetch/sources/bandcamp.py
artfetch/sources/discogs.py
artfetch/sources/musicbrainz.py
artfetch-0.1.0.dist-info/licenses/LICENSE
artfetch-0.1.0.dist-info/METADATA
artfetch-0.1.0.dist-info/WHEEL
artfetch-0.1.0.dist-info/entry_points.txt
artfetch-0.1.0.dist-info/top_level.txt
artfetch-0.1.0.dist-info/RECORD
