Metadata-Version: 2.4
Name: artfetch
Version: 0.1.0
Summary: Automatically tag audio files with album art found on Discogs, Bandcamp or Musicbrainz.
Author-email: Johannes Schleicher <j_schleicher@protonmail.com>
Classifier: Programming Language :: Python :: 3
Classifier: Development Status :: 4 - Beta
Classifier: Operating System :: OS Independent
Classifier: Topic :: Multimedia
Classifier: Topic :: Multimedia :: Sound/Audio :: Editors
Requires-Python: >=3.9
License-File: LICENSE
Requires-Dist: aiohttp>=3.11
Requires-Dist: discogs_client>=2.3
Requires-Dist: musicbrainzngs>=0.7
Requires-Dist: mutagen>=1.47
Requires-Dist: Pillow>=11
Requires-Dist: Requests>=2.32
Requires-Dist: rich>=13.9
Requires-Dist: rich_pixels>=3.0
Requires-Dist: beetcamp>=0.21
Requires-Dist: readchar>=4
Dynamic: license-file
